rapidash/__init__.py
rapidash/cli/__init__.py
rapidash/cli/mock.py
rapidash/cli/parquet.py
rapidash/cli/workflow.py
rapidash/database/__init__.py
rapidash/database/check.py
rapidash/database/connection.py
rapidash/database/cursor.py
rapidash/database/db.py
rapidash/database/insert.py
rapidash/database/schema.py
rapidash/mock/__init__.py
rapidash/mock/arrow.py
rapidash/mock/code.py
rapidash/mock/datatype.py
rapidash/mock/date.py
rapidash/mock/decimal.py
rapidash/mock/gen.py
rapidash/mock/schema.py
rapidash/mock/time.py
rapidash/util/__init__.py
rapidash/util/show.py
rapidash/work/__init__.py
rapidash/work/mock.py
rapidash/work/read.py
rapidash/work/write.py
rapidash-0.0.6.dist-info/LICENSE
rapidash-0.0.6.dist-info/METADATA
rapidash-0.0.6.dist-info/WHEEL
rapidash-0.0.6.dist-info/entry_points.txt
rapidash-0.0.6.dist-info/top_level.txt
rapidash-0.0.6.dist-info/zip-safe
rapidash-0.0.6.dist-info/RECORD
