Metadata-Version: 2.1
Name: rapidash
Version: 0.0.6
Summary: exchange data between database or parquet files
Home-page: https://github.com/lipicoder/rapidash
Author: lipi,zhujw
Author-email: lipi <lipicoder@qq.com>, zhujw <kratoswittgenstein@gmail.com>
License: MIT License
Project-URL: Bug Tracker, https://github.com/lipicoder/rapidash/issues
Project-URL: Homepage, https://github.com/lipicoder/rapidash
Classifier: Programming Language :: Python :: 3
Classifier: License :: OSI Approved :: MIT License
Classifier: Operating System :: OS Independent
License-File: LICENSE
Requires-Dist: pyarrow (==9.0.0)
Requires-Dist: click (==8.1.3)
Requires-Dist: psycopg (==3.1.4)
Requires-Dist: PyYAML (==6.0)
Requires-Dist: pytz (==2022.2.1)
